django_messaging_subscription-0.8.0.dist-info/DESCRIPTION.rst
django_messaging_subscription-0.8.0.dist-info/METADATA
django_messaging_subscription-0.8.0.dist-info/metadata.json
django_messaging_subscription-0.8.0.dist-info/RECORD
django_messaging_subscription-0.8.0.dist-info/top_level.txt
django_messaging_subscription-0.8.0.dist-info/WHEEL
subscription/__init__.py
subscription/admin.py
subscription/api.py
subscription/forms.py
subscription/models.py
subscription/tasks.py
subscription/tests.py
subscription/urls.py
subscription/views.py
subscription/fixtures/initial_data.json
subscription/fixtures/test.json
subscription/fixtures/test_subsend.json
subscription/migrations/0001_initial.py
subscription/migrations/0002_auto__add_field_messageset_default_schedule.py
subscription/migrations/__init__.py
subscription/templates/.DS_Store
subscription/templates/admin/.DS_Store
subscription/templates/admin/subscription/.DS_Store
subscription/templates/admin/subscription/message/change_list.html
subscription/templates/custom_admin/upload.html
