Metadata-Version: 2.0
Name: django-messaging-subscription
Version: 0.8.0
Summary: A RESTful API for managing messaging content, subscriptions and sending via Vumi-go
Home-page: https://github.com/westerncapelabs/django-messaging-subscription
Author: Western Cape Labs
Author-email: devops@westerncapelabs.com
License: BSD
Platform: UNKNOWN
Classifier: Development Status :: 4 - Beta
Classifier: Intended Audience :: Developers
Classifier: License :: OSI Approved :: BSD License
Classifier: Operating System :: POSIX
Classifier: Programming Language :: Python
Classifier: Topic :: Software Development :: Libraries :: Python Modules
Classifier: Topic :: System :: Networking
Requires-Dist: Django
Requires-Dist: django-tastypie (==0.12.2)
Requires-Dist: South
Requires-Dist: gunicorn (==19.0.0)
Requires-Dist: django-celery (==3.1.10)
Requires-Dist: go-http (==0.3.0)
